parse2excel/__init__.py
parse2excel/parse2excel.py
parse2excel-2022.9.1.dist-info/LICENSE
parse2excel-2022.9.1.dist-info/METADATA
parse2excel-2022.9.1.dist-info/WHEEL
parse2excel-2022.9.1.dist-info/entry_points.txt
parse2excel-2022.9.1.dist-info/top_level.txt
parse2excel-2022.9.1.dist-info/RECORD
