Metadata-Version: 2.1
Name: parse2excel
Version: 2022.9.1
Summary: Parsing text files with TextFSM and export to SQLite/Excel with configuration file
Author: Umur Arslan
License: MIT License        
Project-URL: Homepage, https://github.com/umurarslan/parse2excel
Classifier: Programming Language :: Python :: 3
Classifier: License :: OSI Approved :: MIT License
Classifier: Operating System :: OS Independent
Requires-Python: >=3.9
License-File: LICENSE
Requires-Dist: textfsm (>=1.1.0)
Requires-Dist: openpyxl (>=3.0)
Requires-Dist: PyYAML (>=5.4.1)
